py_capio_cl-1.3.1.dist-info/RECORD
py_capio_cl-1.3.1.dist-info/WHEEL
py_capio_cl-1.3.1.dist-info/METADATA
py_capio_cl-1.3.1.dist-info/licenses/LICENSE
include/httplib.h
include/jsoncons/allocator_set.hpp
include/jsoncons/json_visitor.hpp
include/jsoncons/encode_json.hpp
include/jsoncons/json_encoder.hpp
include/jsoncons/json.hpp
include/jsoncons/staj_cursor.hpp
include/jsoncons/json_array.hpp
include/jsoncons/source_adaptor.hpp
include/jsoncons/json_filter.hpp
include/jsoncons/allocator_holder.hpp
include/jsoncons/conversion_result.hpp
include/jsoncons/pretty_print.hpp
include/jsoncons/typed_array_view.hpp
include/jsoncons/diagnostics_visitor.hpp
include/jsoncons/json_decoder.hpp
include/jsoncons/json_object.hpp
include/jsoncons/json_type.hpp
include/jsoncons/json_reader.hpp
include/jsoncons/conv_error.hpp
include/jsoncons/json_options.hpp
include/jsoncons/decode_json.hpp
include/jsoncons/json_exception.hpp
include/jsoncons/staj_event_reader.hpp
include/jsoncons/text_source_adaptor.hpp
include/jsoncons/diagnostics_visitor2.hpp
include/jsoncons/json_parser.hpp
include/jsoncons/source.hpp
include/jsoncons/basic_json.hpp
include/jsoncons/sink.hpp
include/jsoncons/staj_iterator.hpp
include/jsoncons/staj_event.hpp
include/jsoncons/json_cursor.hpp
include/jsoncons/json_type_traits.hpp
include/jsoncons/json_error.hpp
include/jsoncons/item_event_visitor.hpp
include/jsoncons/json_fwd.hpp
include/jsoncons/ser_util.hpp
include/jsoncons/semantic_tag.hpp
include/jsoncons/config/jsoncons_config.hpp
include/jsoncons/config/compiler_support.hpp
include/jsoncons/config/version.hpp
include/jsoncons/reflect/reflect_traits_gen.hpp
include/jsoncons/reflect/json_conv_traits.hpp
include/jsoncons/reflect/encode_traits.hpp
include/jsoncons/reflect/decode_traits.hpp
include/jsoncons/detail/grisu3.hpp
include/jsoncons/detail/utility.hpp
include/jsoncons/detail/span.hpp
include/jsoncons/detail/expected.hpp
include/jsoncons/detail/endian.hpp
include/jsoncons/detail/optional.hpp
include/jsoncons/detail/string_view.hpp
include/jsoncons/detail/make_obj_using_allocator.hpp
