Metadata-Version: 2.2
Name: py_capio_cl
Version: 1.3.1
Summary: Python bindings for the CAPIO-CL coordination language
Author-Email: Marco Edoardo Santimaria <marcoedoardo.santimaria@unito.it>
License: MIT
Project-URL: Homepage, https://capio.hpc4ai.it
Project-URL: Documentation, https://capio.hpc4ai.it/docs/coord-language/
Project-URL: Repository, https://github.com/High-Performance-IO/CAPIO-CL
Project-URL: Issues, https://github.com/High-Performance-IO/CAPIO-CL/issues
Requires-Python: >=3.10
Requires-Dist: requests==2.32.5
